optimalgrouping/__init__.py
optimalgrouping/optimalgrouping.py
optimalgrouping-1.0.4.data/scripts/optimal_binning.py
optimalgrouping-1.0.4.dist-info/LICENSE
optimalgrouping-1.0.4.dist-info/METADATA
optimalgrouping-1.0.4.dist-info/WHEEL
optimalgrouping-1.0.4.dist-info/top_level.txt
optimalgrouping-1.0.4.dist-info/RECORD
